setup.py
./runstat.py
./test_runstat.py
runstat.egg-info/PKG-INFO
runstat.egg-info/SOURCES.txt
runstat.egg-info/dependency_links.txt
runstat.egg-info/requires.txt
runstat.egg-info/top_level.txt