Metadata-Version: 1.1
Name: runstat
Version: 1.0.0
Summary: Implementation of running variance/standard deviation.
Home-page: https://github.com/pelkmanslab/brainy
Author: Yauhen Yakimovich
Author-email: yauhen.yakimovich@uzh.ch
License: MIT
Download-URL: https://github.com/ewiger/runstat/tarball/master
Platform: Linux
Platform: OS-X
Classifier: Programming Language :: Python
Classifier: Programming Language :: Unix Shell
Classifier: Programming Language :: C++
Classifier: Development Status :: 4 - Beta
Classifier: Operating System :: POSIX :: Linux
Classifier: Operating System :: MacOS
